mbed_cloud/__init__.py
mbed_cloud/_build_info.py
mbed_cloud/_version.py
mbed_cloud/configuration.py
mbed_cloud/core.py
mbed_cloud/decorators.py
mbed_cloud/exceptions.py
mbed_cloud/filters.py
mbed_cloud/pagination.py
mbed_cloud/utils.py
mbed_cloud/_backends/__init__.py
mbed_cloud/_backends/billing/README.md
mbed_cloud/_backends/billing/__init__.py
mbed_cloud/_backends/billing/api_client.py
mbed_cloud/_backends/billing/configuration.py
mbed_cloud/_backends/billing/rest.py
mbed_cloud/_backends/billing/apis/__init__.py
mbed_cloud/_backends/billing/apis/default_api.py
mbed_cloud/_backends/billing/docs/ActiveServicePackage.md
mbed_cloud/_backends/billing/docs/AggregatedQuotaUsageReport.md
mbed_cloud/_backends/billing/docs/BadRequestErrorResponse.md
mbed_cloud/_backends/billing/docs/BadRequestErrorResponseField.md
mbed_cloud/_backends/billing/docs/BillingReportRawDataResponse.md
mbed_cloud/_backends/billing/docs/DefaultApi.md
mbed_cloud/_backends/billing/docs/ForbiddenErrorResponse.md
mbed_cloud/_backends/billing/docs/InternalServerErrorResponse.md
mbed_cloud/_backends/billing/docs/PendingServicePackage.md
mbed_cloud/_backends/billing/docs/PreviousServicePackage.md
mbed_cloud/_backends/billing/docs/QuotaUsageReport.md
mbed_cloud/_backends/billing/docs/ReportAccountContactInfo.md
mbed_cloud/_backends/billing/docs/ReportBillingData.md
mbed_cloud/_backends/billing/docs/ReportNotFoundErrorResponse.md
mbed_cloud/_backends/billing/docs/ReportResponse.md
mbed_cloud/_backends/billing/docs/ServicePackageMetadata.md
mbed_cloud/_backends/billing/docs/ServicePackageQuota.md
mbed_cloud/_backends/billing/docs/ServicePackageQuotaHistoryItem.md
mbed_cloud/_backends/billing/docs/ServicePackageQuotaHistoryReservation.md
mbed_cloud/_backends/billing/docs/ServicePackageQuotaHistoryResponse.md
mbed_cloud/_backends/billing/docs/ServicePackageQuotaHistoryServicePackage.md
mbed_cloud/_backends/billing/docs/ServicePackageReport.md
mbed_cloud/_backends/billing/docs/ServicePackagesResponse.md
mbed_cloud_sdk-2.2.0.dist-info/LICENCE
mbed_cloud_sdk-2.2.0.dist-info/METADATA
mbed_cloud_sdk-2.2.0.dist-info/WHEEL
mbed_cloud_sdk-2.2.0.dist-info/top_level.txt
mbed_cloud_sdk-2.2.0.dist-info/RECORD
