Metadata-Version: 2.1
Name: mbed-cloud-sdk
Version: 2.2.0
Summary: Pelion Device Management Python SDK
Home-page: https://github.com/ARMmbed/mbed-cloud-sdk-python
Author: Arkadiusz Zaluski, Graham Hammond, David Hyman, Herman Schistad
Author-email: support@mbed.com
License: Apache 2.0
Keywords: Arm Pelion Device Management Mbed Cloud SDK
Platform: UNKNOWN
Classifier: Development Status :: 5 - Production/Stable
Classifier: Intended Audience :: Developers
Classifier: License :: OSI Approved :: Apache Software License
Classifier: Programming Language :: Python :: 2
Classifier: Programming Language :: Python :: 2.7
Classifier: Programming Language :: Python :: 3
Classifier: Programming Language :: Python :: 3.4
Classifier: Programming Language :: Python :: 3.5
Classifier: Programming Language :: Python :: 3.6
Classifier: Programming Language :: Python :: 3.7
Classifier: Programming Language :: Python
Classifier: Topic :: Internet
Classifier: Topic :: Software Development :: Embedded Systems
Classifier: Topic :: Software Development :: Object Brokering
Requires-Python: >=2.7.10, !=3.0.*, !=3.1.*, !=3.2.*, !=3.3.*, !=3.4.0, !=3.4.1, !=3.4.2, <4
Requires-Dist: certifi (>=2017)
Requires-Dist: future (>=0.16)
Requires-Dist: python-dateutil (>=2)
Requires-Dist: python-dotenv (>=0.8.2)
Requires-Dist: pytz (>=2019)
Requires-Dist: requests (>=2.20)
Requires-Dist: six (>=1.10)
Requires-Dist: urllib3 (>=1.15)
